{
  "entries": [
    {
      "id": "06.12.2025_ensemble_champion_1765394539.194402",
      "date": "2025-12-10T19:22:19.194408",
      "draw_date": "06.12.2025",
      "predicted_numbers": [
        33,
        34,
        6,
        26,
        28,
        29
      ],
      "actual_numbers": [
        33,
        35,
        37,
        15,
        26,
        27
      ],
      "matches": 2,
      "predicted_sz": 1,
      "actual_sz": 2,
      "sz_match": false,
      "method": "ensemble_champion",
      "provider": "ensemble",
      "confidence": 90,
      "strategy": "Voting aus 6 KI-Vorhersagen"
    },
    {
      "id": "06.12.2025_neural_network_1765394539.194444",
      "date": "2025-12-10T19:22:19.194446",
      "draw_date": "06.12.2025",
      "predicted_numbers": [
        34,
        6,
        45,
        47,
        22,
        29
      ],
      "actual_numbers": [
        33,
        35,
        37,
        15,
        26,
        27
      ],
      "matches": 0,
      "predicted_sz": 1,
      "actual_sz": 2,
      "sz_match": false,
      "method": "neural_network",
      "provider": "local_ml",
      "confidence": 85.42125548463083,
      "strategy": ""
    },
    {
      "id": "06.12.2025_lstm_1765394539.194457",
      "date": "2025-12-10T19:22:19.194458",
      "draw_date": "06.12.2025",
      "predicted_numbers": [
        33,
        35,
        37,
        26,
        27,
        28
      ],
      "actual_numbers": [
        33,
        35,
        37,
        15,
        26,
        27
      ],
      "matches": 5,
      "predicted_sz": 7,
      "actual_sz": 2,
      "sz_match": false,
      "method": "lstm",
      "provider": "local_ml",
      "confidence": 77.98939112292064,
      "strategy": ""
    },
    {
      "id": "06.12.2025_random_forest_1765394539.194465",
      "date": "2025-12-10T19:22:19.194466",
      "draw_date": "06.12.2025",
      "predicted_numbers": [
        1,
        4,
        11,
        43,
        49,
        25
      ],
      "actual_numbers": [
        33,
        35,
        37,
        15,
        26,
        27
      ],
      "matches": 0,
      "predicted_sz": 3,
      "actual_sz": 2,
      "sz_match": false,
      "method": "random_forest",
      "provider": "local_ml",
      "confidence": 68.98451918233295,
      "strategy": ""
    },
    {
      "id": "06.12.2025_bayesian_1765394539.194471",
      "date": "2025-12-10T19:22:19.194473",
      "draw_date": "06.12.2025",
      "predicted_numbers": [
        9,
        44,
        13,
        20,
        28,
        30
      ],
      "actual_numbers": [
        33,
        35,
        37,
        15,
        26,
        27
      ],
      "matches": 0,
      "predicted_sz": 6,
      "actual_sz": 2,
      "sz_match": false,
      "method": "bayesian",
      "provider": "local_ml",
      "confidence": 81.46475298376836,
      "strategy": ""
    },
    {
      "id": "06.12.2025_monte_carlo_1765394539.194478",
      "date": "2025-12-10T19:22:19.194479",
      "draw_date": "06.12.2025",
      "predicted_numbers": [
        7,
        41,
        11,
        26,
        29,
        31
      ],
      "actual_numbers": [
        33,
        35,
        37,
        15,
        26,
        27
      ],
      "matches": 1,
      "predicted_sz": 5,
      "actual_sz": 2,
      "sz_match": false,
      "method": "monte_carlo",
      "provider": "local_ml",
      "confidence": 89.95932196208517,
      "strategy": ""
    },
    {
      "id": "06.12.2025_ensemble_ml_1765394539.194487",
      "date": "2025-12-10T19:22:19.194488",
      "draw_date": "06.12.2025",
      "predicted_numbers": [
        33,
        34,
        6,
        43,
        26,
        28
      ],
      "actual_numbers": [
        33,
        35,
        37,
        15,
        26,
        27
      ],
      "matches": 2,
      "predicted_sz": 0,
      "actual_sz": 2,
      "sz_match": false,
      "method": "ensemble_ml",
      "provider": "local_ml",
      "confidence": 64.49133782392457,
      "strategy": ""
    },
    {
      "id": "10.12.2025_ensemble_champion_1765656926.07989",
      "date": "2025-12-13T20:15:26.079899",
      "draw_date": "10.12.2025",
      "predicted_numbers": [
        7,
        43,
        49,
        25,
        26,
        28
      ],
      "actual_numbers": [
        3,
        11,
        12,
        13,
        17,
        24
      ],
      "matches": 0,
      "predicted_sz": 1,
      "actual_sz": 8,
      "sz_match": false,
      "method": "ensemble_champion",
      "provider": "ensemble",
      "confidence": 90,
      "strategy": "Voting aus 6 KI-Vorhersagen"
    },
    {
      "id": "10.12.2025_neural_network_1765656926.07991",
      "date": "2025-12-13T20:15:26.079912",
      "draw_date": "10.12.2025",
      "predicted_numbers": [
        34,
        3,
        43,
        45,
        47,
        25
      ],
      "actual_numbers": [
        3,
        11,
        12,
        13,
        17,
        24
      ],
      "matches": 1,
      "predicted_sz": 1,
      "actual_sz": 8,
      "sz_match": false,
      "method": "neural_network",
      "provider": "local_ml",
      "confidence": 66.36708825432495,
      "strategy": ""
    },
    {
      "id": "10.12.2025_lstm_1765656926.079919",
      "date": "2025-12-13T20:15:26.079920",
      "draw_date": "10.12.2025",
      "predicted_numbers": [
        33,
        35,
        37,
        26,
        27,
        28
      ],
      "actual_numbers": [
        3,
        11,
        12,
        13,
        17,
        24
      ],
      "matches": 0,
      "predicted_sz": 7,
      "actual_sz": 8,
      "sz_match": false,
      "method": "lstm",
      "provider": "local_ml",
      "confidence": 75.88708679221797,
      "strategy": ""
    },
    {
      "id": "10.12.2025_random_forest_1765656926.079926",
      "date": "2025-12-13T20:15:26.079927",
      "draw_date": "10.12.2025",
      "predicted_numbers": [
        4,
        7,
        10,
        11,
        49,
        31
      ],
      "actual_numbers": [
        3,
        11,
        12,
        13,
        17,
        24
      ],
      "matches": 1,
      "predicted_sz": 0,
      "actual_sz": 8,
      "sz_match": false,
      "method": "random_forest",
      "provider": "local_ml",
      "confidence": 79.60856808460944,
      "strategy": ""
    },
    {
      "id": "10.12.2025_bayesian_1765656926.079933",
      "date": "2025-12-13T20:15:26.079934",
      "draw_date": "10.12.2025",
      "predicted_numbers": [
        9,
        44,
        13,
        20,
        28,
        30
      ],
      "actual_numbers": [
        3,
        11,
        12,
        13,
        17,
        24
      ],
      "matches": 1,
      "predicted_sz": 6,
      "actual_sz": 8,
      "sz_match": false,
      "method": "bayesian",
      "provider": "local_ml",
      "confidence": 71.21175268045253,
      "strategy": ""
    },
    {
      "id": "10.12.2025_monte_carlo_1765656926.079941",
      "date": "2025-12-13T20:15:26.079942",
      "draw_date": "10.12.2025",
      "predicted_numbers": [
        6,
        7,
        49,
        22,
        25,
        26
      ],
      "actual_numbers": [
        3,
        11,
        12,
        13,
        17,
        24
      ],
      "matches": 0,
      "predicted_sz": 3,
      "actual_sz": 8,
      "sz_match": false,
      "method": "monte_carlo",
      "provider": "local_ml",
      "confidence": 65.49420493384144,
      "strategy": ""
    },
    {
      "id": "10.12.2025_ensemble_ml_1765656926.079949",
      "date": "2025-12-13T20:15:26.079950",
      "draw_date": "10.12.2025",
      "predicted_numbers": [
        7,
        43,
        25,
        26,
        28,
        29
      ],
      "actual_numbers": [
        3,
        11,
        12,
        13,
        17,
        24
      ],
      "matches": 0,
      "predicted_sz": 5,
      "actual_sz": 8,
      "sz_match": false,
      "method": "ensemble_ml",
      "provider": "local_ml",
      "confidence": 84.74476843378488,
      "strategy": ""
    },
    {
      "id": "10.12.2025_ensemble_champion_1765683629.401655",
      "date": "2025-12-14T03:40:29.401661",
      "draw_date": "10.12.2025",
      "predicted_numbers": [
        7,
        11,
        12,
        13,
        22,
        29
      ],
      "actual_numbers": [
        3,
        11,
        12,
        13,
        17,
        24
      ],
      "matches": 3,
      "predicted_sz": 3,
      "actual_sz": 8,
      "sz_match": false,
      "method": "ensemble_champion",
      "provider": "ensemble",
      "confidence": 90,
      "strategy": "Voting aus 6 KI-Vorhersagen"
    },
    {
      "id": "10.12.2025_neural_network_1765683629.401672",
      "date": "2025-12-14T03:40:29.401674",
      "draw_date": "10.12.2025",
      "predicted_numbers": [
        34,
        7,
        11,
        22,
        25,
        29
      ],
      "actual_numbers": [
        3,
        11,
        12,
        13,
        17,
        24
      ],
      "matches": 1,
      "predicted_sz": 3,
      "actual_sz": 8,
      "sz_match": false,
      "method": "neural_network",
      "provider": "local_ml",
      "confidence": 65.71011350644842,
      "strategy": ""
    },
    {
      "id": "10.12.2025_lstm_1765683629.401684",
      "date": "2025-12-14T03:40:29.401685",
      "draw_date": "10.12.2025",
      "predicted_numbers": [
        11,
        12,
        13,
        15,
        17,
        24
      ],
      "actual_numbers": [
        3,
        11,
        12,
        13,
        17,
        24
      ],
      "matches": 5,
      "predicted_sz": 9,
      "actual_sz": 8,
      "sz_match": false,
      "method": "lstm",
      "provider": "local_ml",
      "confidence": 61.38959956650689,
      "strategy": ""
    },
    {
      "id": "10.12.2025_random_forest_1765683629.401691",
      "date": "2025-12-14T03:40:29.401693",
      "draw_date": "10.12.2025",
      "predicted_numbers": [
        7,
        43,
        49,
        22,
        25,
        29
      ],
      "actual_numbers": [
        3,
        11,
        12,
        13,
        17,
        24
      ],
      "matches": 0,
      "predicted_sz": 0,
      "actual_sz": 8,
      "sz_match": false,
      "method": "random_forest",
      "provider": "local_ml",
      "confidence": 65.87508673013299,
      "strategy": ""
    },
    {
      "id": "10.12.2025_bayesian_1765683629.401698",
      "date": "2025-12-14T03:40:29.401700",
      "draw_date": "10.12.2025",
      "predicted_numbers": [
        12,
        13,
        44,
        20,
        28,
        30
      ],
      "actual_numbers": [
        3,
        11,
        12,
        13,
        17,
        24
      ],
      "matches": 2,
      "predicted_sz": 5,
      "actual_sz": 8,
      "sz_match": false,
      "method": "bayesian",
      "provider": "local_ml",
      "confidence": 61.48002117821817,
      "strategy": ""
    },
    {
      "id": "10.12.2025_monte_carlo_1765683629.401705",
      "date": "2025-12-14T03:40:29.401706",
      "draw_date": "10.12.2025",
      "predicted_numbers": [
        33,
        4,
        11,
        43,
        29,
        31
      ],
      "actual_numbers": [
        3,
        11,
        12,
        13,
        17,
        24
      ],
      "matches": 1,
      "predicted_sz": 2,
      "actual_sz": 8,
      "sz_match": false,
      "method": "monte_carlo",
      "provider": "local_ml",
      "confidence": 74.63567935353676,
      "strategy": ""
    },
    {
      "id": "10.12.2025_ensemble_ml_1765683629.401714",
      "date": "2025-12-14T03:40:29.401715",
      "draw_date": "10.12.2025",
      "predicted_numbers": [
        33,
        41,
        11,
        12,
        13,
        49
      ],
      "actual_numbers": [
        3,
        11,
        12,
        13,
        17,
        24
      ],
      "matches": 3,
      "predicted_sz": 6,
      "actual_sz": 8,
      "sz_match": false,
      "method": "ensemble_ml",
      "provider": "local_ml",
      "confidence": 79.79689294132478,
      "strategy": ""
    },
    {
      "id": "13.12.2025_ensemble_champion_1765997884.077857",
      "date": "2025-12-17T18:58:04.077864",
      "draw_date": "13.12.2025",
      "predicted_numbers": [
        1,
        6,
        11,
        12,
        13,
        29
      ],
      "actual_numbers": [
        32,
        37,
        6,
        11,
        45,
        21
      ],
      "matches": 2,
      "predicted_sz": 3,
      "actual_sz": 3,
      "sz_match": true,
      "method": "ensemble_champion",
      "provider": "ensemble",
      "confidence": 90,
      "strategy": "Voting aus 6 KI-Vorhersagen"
    },
    {
      "id": "13.12.2025_neural_network_1765997884.077877",
      "date": "2025-12-17T18:58:04.077879",
      "draw_date": "13.12.2025",
      "predicted_numbers": [
        33,
        34,
        11,
        45,
        14,
        29
      ],
      "actual_numbers": [
        32,
        37,
        6,
        11,
        45,
        21
      ],
      "matches": 2,
      "predicted_sz": 3,
      "actual_sz": 3,
      "sz_match": true,
      "method": "neural_network",
      "provider": "local_ml",
      "confidence": 76.60712610180559,
      "strategy": ""
    },
    {
      "id": "13.12.2025_lstm_1765997884.077886",
      "date": "2025-12-17T18:58:04.077887",
      "draw_date": "13.12.2025",
      "predicted_numbers": [
        11,
        12,
        13,
        15,
        17,
        24
      ],
      "actual_numbers": [
        32,
        37,
        6,
        11,
        45,
        21
      ],
      "matches": 1,
      "predicted_sz": 6,
      "actual_sz": 3,
      "sz_match": false,
      "method": "lstm",
      "provider": "local_ml",
      "confidence": 89.90049018673153,
      "strategy": ""
    },
    {
      "id": "13.12.2025_random_forest_1765997884.077893",
      "date": "2025-12-17T18:58:04.077894",
      "draw_date": "13.12.2025",
      "predicted_numbers": [
        1,
        6,
        7,
        11,
        49,
        29
      ],
      "actual_numbers": [
        32,
        37,
        6,
        11,
        45,
        21
      ],
      "matches": 2,
      "predicted_sz": 0,
      "actual_sz": 3,
      "sz_match": false,
      "method": "random_forest",
      "provider": "local_ml",
      "confidence": 61.86782968650203,
      "strategy": ""
    },
    {
      "id": "13.12.2025_bayesian_1765997884.077903",
      "date": "2025-12-17T18:58:04.077904",
      "draw_date": "13.12.2025",
      "predicted_numbers": [
        12,
        13,
        44,
        20,
        28,
        30
      ],
      "actual_numbers": [
        32,
        37,
        6,
        11,
        45,
        21
      ],
      "matches": 0,
      "predicted_sz": 5,
      "actual_sz": 3,
      "sz_match": false,
      "method": "bayesian",
      "provider": "local_ml",
      "confidence": 74.09380681803843,
      "strategy": ""
    },
    {
      "id": "13.12.2025_monte_carlo_1765997884.07791",
      "date": "2025-12-17T18:58:04.077911",
      "draw_date": "13.12.2025",
      "predicted_numbers": [
        1,
        6,
        41,
        49,
        26,
        31
      ],
      "actual_numbers": [
        32,
        37,
        6,
        11,
        45,
        21
      ],
      "matches": 1,
      "predicted_sz": 9,
      "actual_sz": 3,
      "sz_match": false,
      "method": "monte_carlo",
      "provider": "local_ml",
      "confidence": 73.6896553874457,
      "strategy": ""
    },
    {
      "id": "13.12.2025_ensemble_ml_1765997884.077918",
      "date": "2025-12-17T18:58:04.077920",
      "draw_date": "13.12.2025",
      "predicted_numbers": [
        10,
        11,
        12,
        13,
        25,
        26
      ],
      "actual_numbers": [
        32,
        37,
        6,
        11,
        45,
        21
      ],
      "matches": 1,
      "predicted_sz": 7,
      "actual_sz": 3,
      "sz_match": false,
      "method": "ensemble_ml",
      "provider": "local_ml",
      "confidence": 63.69716398281692,
      "strategy": ""
    },
    {
      "id": "13.12.2025_ensemble_champion_1765999411.728206",
      "date": "2025-12-17T19:23:31.728216",
      "draw_date": "13.12.2025",
      "predicted_numbers": [
        33,
        37,
        6,
        7,
        11,
        13
      ],
      "actual_numbers": [
        32,
        37,
        6,
        11,
        45,
        21
      ],
      "matches": 3,
      "predicted_sz": 7,
      "actual_sz": 3,
      "sz_match": false,
      "method": "ensemble_champion",
      "provider": "ensemble",
      "confidence": 90,
      "strategy": "Voting aus 6 KI-Vorhersagen"
    },
    {
      "id": "13.12.2025_neural_network_1765999411.728231",
      "date": "2025-12-17T19:23:31.728233",
      "draw_date": "13.12.2025",
      "predicted_numbers": [
        34,
        6,
        14,
        19,
        22,
        25
      ],
      "actual_numbers": [
        32,
        37,
        6,
        11,
        45,
        21
      ],
      "matches": 1,
      "predicted_sz": 7,
      "actual_sz": 3,
      "sz_match": false,
      "method": "neural_network",
      "provider": "local_ml",
      "confidence": 71.36850091545594,
      "strategy": ""
    },
    {
      "id": "13.12.2025_lstm_1765999411.728241",
      "date": "2025-12-17T19:23:31.728242",
      "draw_date": "13.12.2025",
      "predicted_numbers": [
        32,
        37,
        11,
        13,
        45,
        21
      ],
      "actual_numbers": [
        32,
        37,
        6,
        11,
        45,
        21
      ],
      "matches": 5,
      "predicted_sz": 9,
      "actual_sz": 3,
      "sz_match": false,
      "method": "lstm",
      "provider": "local_ml",
      "confidence": 71.32096558547207,
      "strategy": ""
    },
    {
      "id": "13.12.2025_random_forest_1765999411.728247",
      "date": "2025-12-17T19:23:31.728249",
      "draw_date": "13.12.2025",
      "predicted_numbers": [
        33,
        4,
        7,
        11,
        26,
        29
      ],
      "actual_numbers": [
        32,
        37,
        6,
        11,
        45,
        21
      ],
      "matches": 1,
      "predicted_sz": 6,
      "actual_sz": 3,
      "sz_match": false,
      "method": "random_forest",
      "provider": "local_ml",
      "confidence": 81.40103550243803,
      "strategy": ""
    },
    {
      "id": "13.12.2025_bayesian_1765999411.728254",
      "date": "2025-12-17T19:23:31.728255",
      "draw_date": "13.12.2025",
      "predicted_numbers": [
        37,
        12,
        13,
        44,
        20,
        30
      ],
      "actual_numbers": [
        32,
        37,
        6,
        11,
        45,
        21
      ],
      "matches": 1,
      "predicted_sz": 0,
      "actual_sz": 3,
      "sz_match": false,
      "method": "bayesian",
      "provider": "local_ml",
      "confidence": 87.55827484147423,
      "strategy": ""
    },
    {
      "id": "13.12.2025_monte_carlo_1765999411.72826",
      "date": "2025-12-17T19:23:31.728261",
      "draw_date": "13.12.2025",
      "predicted_numbers": [
        33,
        7,
        11,
        49,
        25,
        31
      ],
      "actual_numbers": [
        32,
        37,
        6,
        11,
        45,
        21
      ],
      "matches": 1,
      "predicted_sz": 1,
      "actual_sz": 3,
      "sz_match": false,
      "method": "monte_carlo",
      "provider": "local_ml",
      "confidence": 67.10410724432455,
      "strategy": ""
    },
    {
      "id": "13.12.2025_ensemble_ml_1765999411.728267",
      "date": "2025-12-17T19:23:31.728268",
      "draw_date": "13.12.2025",
      "predicted_numbers": [
        33,
        37,
        6,
        7,
        11,
        13
      ],
      "actual_numbers": [
        32,
        37,
        6,
        11,
        45,
        21
      ],
      "matches": 3,
      "predicted_sz": 4,
      "actual_sz": 3,
      "sz_match": false,
      "method": "ensemble_ml",
      "provider": "local_ml",
      "confidence": 70.25184814999291,
      "strategy": ""
    },
    {
      "id": "13.12.2025_ensemble_champion_1766141048.470637",
      "date": "2025-12-19T10:44:08.470646",
      "draw_date": "13.12.2025",
      "predicted_numbers": [
        2,
        37,
        9,
        43,
        13,
        28
      ],
      "actual_numbers": [
        32,
        37,
        6,
        11,
        45,
        21
      ],
      "matches": 1,
      "predicted_sz": 9,
      "actual_sz": 3,
      "sz_match": false,
      "method": "ensemble_champion",
      "provider": "ensemble",
      "confidence": 95,
      "strategy": "Gewichtetes Voting aus 21 Vorhersagen",
      "gewinnklasse": null,
      "new_weight": 1.6
    },
    {
      "id": "13.12.2025_cold_numbers_1766141048.470691",
      "date": "2025-12-19T10:44:08.470694",
      "draw_date": "13.12.2025",
      "predicted_numbers": [
        32,
        1,
        41,
        43,
        46,
        24
      ],
      "actual_numbers": [
        32,
        37,
        6,
        11,
        45,
        21
      ],
      "matches": 1,
      "predicted_sz": 7,
      "actual_sz": 3,
      "sz_match": false,
      "method": "cold_numbers",
      "provider": "local_strategy",
      "confidence": 68.91310619562631,
      "strategy": "Kalte/seltene Zahlen bevorzugt",
      "gewinnklasse": null,
      "new_weight": 1.6
    },
    {
      "id": "13.12.2025_overdue_1766141048.470722",
      "date": "2025-12-19T10:44:08.470724",
      "draw_date": "13.12.2025",
      "predicted_numbers": [
        5,
        40,
        43,
        14,
        23,
        31
      ],
      "actual_numbers": [
        32,
        37,
        6,
        11,
        45,
        21
      ],
      "matches": 0,
      "predicted_sz": 0,
      "actual_sz": 3,
      "sz_match": false,
      "method": "overdue",
      "provider": "local_strategy",
      "confidence": 65.1315312948591,
      "strategy": "\u00dcberf\u00e4llige Zahlen mit gro\u00dfer L\u00fccke",
      "gewinnklasse": null,
      "new_weight": 0.85
    },
    {
      "id": "13.12.2025_odd_even_33_1766141048.470755",
      "date": "2025-12-19T10:44:08.470766",
      "draw_date": "13.12.2025",
      "predicted_numbers": [
        33,
        2,
        43,
        47,
        20,
        30
      ],
      "actual_numbers": [
        32,
        37,
        6,
        11,
        45,
        21
      ],
      "matches": 0,
      "predicted_sz": 6,
      "actual_sz": 3,
      "sz_match": false,
      "method": "odd_even_33",
      "provider": "local_strategy",
      "confidence": 63.33366060378236,
      "strategy": "Ausgewogene 3:3 Verteilung gerade/ungerade",
      "gewinnklasse": null,
      "new_weight": 0.85
    },
    {
      "id": "13.12.2025_monte_carlo_1766141048.470798",
      "date": "2025-12-19T10:44:08.470799",
      "draw_date": "13.12.2025",
      "predicted_numbers": [
        37,
        40,
        9,
        44,
        20,
        28
      ],
      "actual_numbers": [
        32,
        37,
        6,
        11,
        45,
        21
      ],
      "matches": 1,
      "predicted_sz": 6,
      "actual_sz": 3,
      "sz_match": false,
      "method": "monte_carlo",
      "provider": "local_strategy",
      "confidence": 63.84752337649045,
      "strategy": "Monte-Carlo Simulation (1000 Durchl\u00e4ufe)",
      "gewinnklasse": null,
      "new_weight": 1.6
    },
    {
      "id": "13.12.2025_hot_cold_1766141048.470833",
      "date": "2025-12-19T10:44:08.470835",
      "draw_date": "13.12.2025",
      "predicted_numbers": [
        1,
        37,
        6,
        7,
        41,
        15
      ],
      "actual_numbers": [
        32,
        37,
        6,
        11,
        45,
        21
      ],
      "matches": 2,
      "predicted_sz": 9,
      "actual_sz": 3,
      "sz_match": false,
      "method": "hot_cold",
      "provider": "local_strategy",
      "confidence": 69.29030269037582,
      "strategy": "Kombination aus hei\u00dfen und kalten Zahlen",
      "gewinnklasse": null,
      "new_weight": 2.35
    },
    {
      "id": "13.12.2025_odd_even_42_1766141048.47086",
      "date": "2025-12-19T10:44:08.470862",
      "draw_date": "13.12.2025",
      "predicted_numbers": [
        3,
        7,
        40,
        9,
        43,
        28
      ],
      "actual_numbers": [
        32,
        37,
        6,
        11,
        45,
        21
      ],
      "matches": 0,
      "predicted_sz": 1,
      "actual_sz": 3,
      "sz_match": false,
      "method": "odd_even_42",
      "provider": "local_strategy",
      "confidence": 65.74601305237064,
      "strategy": "4 ungerade, 2 gerade Zahlen",
      "gewinnklasse": null,
      "new_weight": 0.85
    },
    {
      "id": "13.12.2025_decade_balance_1766141048.470905",
      "date": "2025-12-19T10:44:08.470907",
      "draw_date": "13.12.2025",
      "predicted_numbers": [
        3,
        38,
        8,
        49,
        20,
        30
      ],
      "actual_numbers": [
        32,
        37,
        6,
        11,
        45,
        21
      ],
      "matches": 0,
      "predicted_sz": 4,
      "actual_sz": 3,
      "sz_match": false,
      "method": "decade_balance",
      "provider": "local_strategy",
      "confidence": 63.887076155059916,
      "strategy": "Ausgewogene Dekaden-Verteilung",
      "gewinnklasse": null,
      "new_weight": 0.85
    },
    {
      "id": "13.12.2025_no_consecutive_1766141048.470948",
      "date": "2025-12-19T10:44:08.470950",
      "draw_date": "13.12.2025",
      "predicted_numbers": [
        34,
        37,
        11,
        47,
        29,
        31
      ],
      "actual_numbers": [
        32,
        37,
        6,
        11,
        45,
        21
      ],
      "matches": 2,
      "predicted_sz": 8,
      "actual_sz": 3,
      "sz_match": false,
      "method": "no_consecutive",
      "provider": "local_strategy",
      "confidence": 68.66982476587013,
      "strategy": "Keine aufeinanderfolgenden Zahlen",
      "gewinnklasse": null,
      "new_weight": 2.35
    },
    {
      "id": "13.12.2025_random_forest_1766141048.470972",
      "date": "2025-12-19T10:44:08.470974",
      "draw_date": "13.12.2025",
      "predicted_numbers": [
        15,
        16,
        47,
        21,
        28,
        29
      ],
      "actual_numbers": [
        32,
        37,
        6,
        11,
        45,
        21
      ],
      "matches": 1,
      "predicted_sz": 9,
      "actual_sz": 3,
      "sz_match": false,
      "method": "random_forest",
      "provider": "local_strategy",
      "confidence": 65.39954212404139,
      "strategy": "Random Forest Ensemble",
      "gewinnklasse": null,
      "new_weight": 1.6
    }
  ],
  "stats": {
    "total_entries": 45,
    "avg_matches": 1.33,
    "sz_accuracy": 4.44,
    "three_plus_rate": 15.56,
    "four_plus_rate": 6.67,
    "gewinnklassen_total": {},
    "last_update": "2025-12-19T10:44:08.471920",
    "last_draw": "13.12.2025"
  },
  "by_method": {
    "ensemble_champion": {
      "total_predictions": 6,
      "total_matches": 11,
      "total_possible": 36,
      "sz_correct": 1,
      "three_plus": 2,
      "four_plus": 0,
      "accuracy": 30.56,
      "sz_accuracy": 16.67,
      "three_plus_rate": 33.33
    },
    "neural_network": {
      "total_predictions": 5,
      "total_matches": 5,
      "total_possible": 30,
      "sz_correct": 1,
      "three_plus": 0,
      "four_plus": 0,
      "accuracy": 16.67,
      "sz_accuracy": 20.0,
      "three_plus_rate": 0.0
    },
    "lstm": {
      "total_predictions": 5,
      "total_matches": 16,
      "total_possible": 30,
      "sz_correct": 0,
      "three_plus": 3,
      "four_plus": 3,
      "accuracy": 53.33,
      "sz_accuracy": 0.0,
      "three_plus_rate": 60.0
    },
    "random_forest": {
      "total_predictions": 6,
      "total_matches": 5,
      "total_possible": 36,
      "sz_correct": 0,
      "three_plus": 0,
      "four_plus": 0,
      "accuracy": 13.89,
      "sz_accuracy": 0.0,
      "three_plus_rate": 0.0
    },
    "bayesian": {
      "total_predictions": 5,
      "total_matches": 4,
      "total_possible": 30,
      "sz_correct": 0,
      "three_plus": 0,
      "four_plus": 0,
      "accuracy": 13.33,
      "sz_accuracy": 0.0,
      "three_plus_rate": 0.0
    },
    "monte_carlo": {
      "total_predictions": 6,
      "total_matches": 5,
      "total_possible": 36,
      "sz_correct": 0,
      "three_plus": 0,
      "four_plus": 0,
      "accuracy": 13.89,
      "sz_accuracy": 0.0,
      "three_plus_rate": 0.0
    },
    "ensemble_ml": {
      "total_predictions": 5,
      "total_matches": 9,
      "total_possible": 30,
      "sz_correct": 0,
      "three_plus": 2,
      "four_plus": 0,
      "accuracy": 30.0,
      "sz_accuracy": 0.0,
      "three_plus_rate": 40.0
    },
    "cold_numbers": {
      "total_predictions": 1,
      "total_matches": 1,
      "total_possible": 6,
      "sz_correct": 0,
      "three_plus": 0,
      "four_plus": 0,
      "gewinnklassen": {},
      "accuracy": 16.67,
      "sz_accuracy": 0.0,
      "three_plus_rate": 0.0
    },
    "overdue": {
      "total_predictions": 1,
      "total_matches": 0,
      "total_possible": 6,
      "sz_correct": 0,
      "three_plus": 0,
      "four_plus": 0,
      "gewinnklassen": {},
      "accuracy": 0.0,
      "sz_accuracy": 0.0,
      "three_plus_rate": 0.0
    },
    "odd_even_33": {
      "total_predictions": 1,
      "total_matches": 0,
      "total_possible": 6,
      "sz_correct": 0,
      "three_plus": 0,
      "four_plus": 0,
      "gewinnklassen": {},
      "accuracy": 0.0,
      "sz_accuracy": 0.0,
      "three_plus_rate": 0.0
    },
    "hot_cold": {
      "total_predictions": 1,
      "total_matches": 2,
      "total_possible": 6,
      "sz_correct": 0,
      "three_plus": 0,
      "four_plus": 0,
      "gewinnklassen": {},
      "accuracy": 33.33,
      "sz_accuracy": 0.0,
      "three_plus_rate": 0.0
    },
    "odd_even_42": {
      "total_predictions": 1,
      "total_matches": 0,
      "total_possible": 6,
      "sz_correct": 0,
      "three_plus": 0,
      "four_plus": 0,
      "gewinnklassen": {},
      "accuracy": 0.0,
      "sz_accuracy": 0.0,
      "three_plus_rate": 0.0
    },
    "decade_balance": {
      "total_predictions": 1,
      "total_matches": 0,
      "total_possible": 6,
      "sz_correct": 0,
      "three_plus": 0,
      "four_plus": 0,
      "gewinnklassen": {},
      "accuracy": 0.0,
      "sz_accuracy": 0.0,
      "three_plus_rate": 0.0
    },
    "no_consecutive": {
      "total_predictions": 1,
      "total_matches": 2,
      "total_possible": 6,
      "sz_correct": 0,
      "three_plus": 0,
      "four_plus": 0,
      "gewinnklassen": {},
      "accuracy": 33.33,
      "sz_accuracy": 0.0,
      "three_plus_rate": 0.0
    }
  },
  "by_provider": {}
}