{
  "strategies": {
    "ensemble_champion": {
      "weight": 0.5624463749999998,
      "total_matches": 1,
      "total_predictions": 5,
      "gewinnklassen": {
        "6": 1
      },
      "last_updated": "2025-12-28T03:49:44.997340"
    },
    "s6_cold": {
      "weight": 0.7224999999999999,
      "total_matches": 0,
      "total_predictions": 2,
      "gewinnklassen": {},
      "last_updated": "2025-12-27T20:16:17.685663"
    },
    "s6_sum": {
      "weight": 0.7224999999999999,
      "total_matches": 0,
      "total_predictions": 2,
      "gewinnklassen": {},
      "last_updated": "2025-12-28T03:49:44.997543"
    },
    "s6_position_top3": {
      "weight": 0.7224999999999999,
      "total_matches": 0,
      "total_predictions": 2,
      "gewinnklassen": {},
      "last_updated": "2025-12-28T03:49:44.997521"
    },
    "s6_odd_even": {
      "weight": 0.7224999999999999,
      "total_matches": 0,
      "total_predictions": 2,
      "gewinnklassen": {},
      "last_updated": "2025-12-27T20:16:17.685681"
    },
    "s6_overdue": {
      "weight": 0.85,
      "total_matches": 0,
      "total_predictions": 1,
      "gewinnklassen": {},
      "last_updated": "2025-12-19T11:23:50.242507"
    },
    "s6_no_doubles": {
      "weight": 0.7224999999999999,
      "total_matches": 0,
      "total_predictions": 2,
      "gewinnklassen": {},
      "last_updated": "2025-12-27T20:16:17.685611"
    },
    "s6_delta": {
      "weight": 0.85,
      "total_matches": 0,
      "total_predictions": 1,
      "gewinnklassen": {},
      "last_updated": "2025-12-19T11:23:50.242563"
    },
    "s6_last_var": {
      "weight": 0.7224999999999999,
      "total_matches": 0,
      "total_predictions": 2,
      "gewinnklassen": {},
      "last_updated": "2025-12-26T20:19:12.441190"
    },
    "s6_symmetry": {
      "weight": 0.85,
      "total_matches": 0,
      "total_predictions": 1,
      "gewinnklassen": {},
      "last_updated": "2025-12-19T11:23:50.242624"
    },
    "ml_ensemble_real": {
      "weight": 0.6639074999999999,
      "total_matches": 1,
      "total_predictions": 4,
      "gewinnklassen": {
        "6": 1
      },
      "last_updated": "2025-12-28T03:49:44.997408"
    },
    "ml_neural_network_real": {
      "weight": 0.6639074999999999,
      "total_matches": 1,
      "total_predictions": 4,
      "gewinnklassen": {
        "6": 1
      },
      "last_updated": "2025-12-28T03:49:44.997430"
    },
    "ml_bayesian_real": {
      "weight": 0.6639074999999999,
      "total_matches": 1,
      "total_predictions": 4,
      "gewinnklassen": {
        "6": 1
      },
      "last_updated": "2025-12-28T03:49:44.997383"
    },
    "ml_markov_real": {
      "weight": 1.225223333333333,
      "total_matches": 2,
      "total_predictions": 3,
      "gewinnklassen": {
        "6": 2
      },
      "last_updated": "2025-12-27T20:16:17.685593"
    },
    "ml_reinforcement_real": {
      "weight": 0.5220062499999999,
      "total_matches": 0,
      "total_predictions": 4,
      "gewinnklassen": {},
      "last_updated": "2025-12-28T03:49:44.997450"
    },
    "s6_prime": {
      "weight": 0.7224999999999999,
      "total_matches": 0,
      "total_predictions": 2,
      "gewinnklassen": {},
      "last_updated": "2025-12-26T20:19:12.441257"
    },
    "s6_position_hot": {
      "weight": 0.7224999999999999,
      "total_matches": 0,
      "total_predictions": 2,
      "gewinnklassen": {},
      "last_updated": "2025-12-28T03:49:44.997491"
    },
    "s6_hot": {
      "weight": 0.85,
      "total_matches": 0,
      "total_predictions": 1,
      "gewinnklassen": {},
      "last_updated": "2025-12-24T19:19:51.634942"
    },
    "s6_markov": {
      "weight": 0.85,
      "total_matches": 0,
      "total_predictions": 1,
      "gewinnklassen": {},
      "last_updated": "2025-12-24T19:19:51.634960"
    },
    "s6_monte_carlo": {
      "weight": 0.6141249999999999,
      "total_matches": 0,
      "total_predictions": 3,
      "gewinnklassen": {},
      "last_updated": "2025-12-28T03:49:44.997561"
    },
    "s6_bayesian": {
      "weight": 0.85,
      "total_matches": 0,
      "total_predictions": 1,
      "gewinnklassen": {},
      "last_updated": "2025-12-26T20:19:12.441239"
    },
    "s6_fibonacci": {
      "weight": 0.85,
      "total_matches": 0,
      "total_predictions": 1,
      "gewinnklassen": {},
      "last_updated": "2025-12-28T03:49:44.997470"
    }
  },
  "last_update": "2025-12-28T03:49:45.156554",
  "learning_rate": 0.15
}