{
  "strategies": {
    "ensemble_champion": {
      "weight": 0.5602406460345176,
      "total_matches": 3,
      "total_predictions": 9,
      "gewinnklassen": {
        "6": 3
      },
      "last_updated": "2026-01-06T20:20:05.779948"
    },
    "s6_cold": {
      "weight": 0.6141249999999999,
      "total_matches": 0,
      "total_predictions": 3,
      "gewinnklassen": {},
      "last_updated": "2026-01-03T20:16:19.180944"
    },
    "s6_sum": {
      "weight": 0.5220062499999999,
      "total_matches": 0,
      "total_predictions": 4,
      "gewinnklassen": {},
      "last_updated": "2026-01-06T20:20:05.780606"
    },
    "s6_position_top3": {
      "weight": 0.6141249999999999,
      "total_matches": 0,
      "total_predictions": 3,
      "gewinnklassen": {},
      "last_updated": "2026-01-03T20:16:19.181017"
    },
    "s6_odd_even": {
      "weight": 0.7224999999999999,
      "total_matches": 0,
      "total_predictions": 2,
      "gewinnklassen": {},
      "last_updated": "2025-12-27T20:16:17.685681"
    },
    "s6_overdue": {
      "weight": 0.7224999999999999,
      "total_matches": 0,
      "total_predictions": 2,
      "gewinnklassen": {},
      "last_updated": "2026-01-02T20:19:39.622393"
    },
    "s6_no_doubles": {
      "weight": 0.7224999999999999,
      "total_matches": 0,
      "total_predictions": 2,
      "gewinnklassen": {},
      "last_updated": "2025-12-27T20:16:17.685611"
    },
    "s6_delta": {
      "weight": 0.5220062499999999,
      "total_matches": 0,
      "total_predictions": 4,
      "gewinnklassen": {},
      "last_updated": "2026-01-06T20:20:05.780649"
    },
    "s6_last_var": {
      "weight": 0.6141249999999999,
      "total_matches": 0,
      "total_predictions": 3,
      "gewinnklassen": {},
      "last_updated": "2026-01-02T20:19:39.622444"
    },
    "s6_symmetry": {
      "weight": 0.85,
      "total_matches": 0,
      "total_predictions": 1,
      "gewinnklassen": {},
      "last_updated": "2025-12-19T11:23:50.242624"
    },
    "ml_ensemble_real": {
      "weight": 0.5750487749821427,
      "total_matches": 2,
      "total_predictions": 7,
      "gewinnklassen": {
        "6": 2
      },
      "last_updated": "2026-01-06T20:20:05.780074"
    },
    "ml_neural_network_real": {
      "weight": 0.657189036196071,
      "total_matches": 3,
      "total_predictions": 8,
      "gewinnklassen": {
        "6": 3
      },
      "last_updated": "2026-01-06T20:20:05.779994"
    },
    "ml_bayesian_real": {
      "weight": 0.5080771730205356,
      "total_matches": 2,
      "total_predictions": 8,
      "gewinnklassen": {
        "6": 2
      },
      "last_updated": "2026-01-06T20:20:05.780097"
    },
    "ml_markov_real": {
      "weight": 1.549764542941071,
      "total_matches": 5,
      "total_predictions": 7,
      "gewinnklassen": {
        "6": 3,
        "5": 1
      },
      "last_updated": "2026-01-06T20:20:05.780023"
    },
    "ml_reinforcement_real": {
      "weight": 0.32057708828124987,
      "total_matches": 0,
      "total_predictions": 7,
      "gewinnklassen": {},
      "last_updated": "2026-01-06T20:20:05.780047"
    },
    "s6_prime": {
      "weight": 0.6141249999999999,
      "total_matches": 0,
      "total_predictions": 3,
      "gewinnklassen": {},
      "last_updated": "2026-01-03T20:16:19.180975"
    },
    "s6_position_hot": {
      "weight": 0.7224999999999999,
      "total_matches": 0,
      "total_predictions": 2,
      "gewinnklassen": {},
      "last_updated": "2025-12-28T03:49:44.997491"
    },
    "s6_hot": {
      "weight": 0.7224999999999999,
      "total_matches": 0,
      "total_predictions": 2,
      "gewinnklassen": {},
      "last_updated": "2026-01-02T20:19:39.622463"
    },
    "s6_markov": {
      "weight": 0.6141249999999999,
      "total_matches": 0,
      "total_predictions": 3,
      "gewinnklassen": {},
      "last_updated": "2026-01-04T03:53:06.737060"
    },
    "s6_monte_carlo": {
      "weight": 0.5220062499999999,
      "total_matches": 0,
      "total_predictions": 4,
      "gewinnklassen": {},
      "last_updated": "2026-01-06T20:20:05.780625"
    },
    "s6_bayesian": {
      "weight": 0.7224999999999999,
      "total_matches": 0,
      "total_predictions": 2,
      "gewinnklassen": {},
      "last_updated": "2026-01-03T20:16:19.180997"
    },
    "s6_fibonacci": {
      "weight": 0.6141249999999999,
      "total_matches": 0,
      "total_predictions": 3,
      "gewinnklassen": {},
      "last_updated": "2026-01-06T20:20:05.780567"
    },
    "s6_neural": {
      "weight": 0.85,
      "total_matches": 0,
      "total_predictions": 1,
      "gewinnklassen": {},
      "last_updated": "2026-01-04T03:53:06.736972"
    }
  },
  "last_update": "2026-01-06T20:20:05.976769",
  "learning_rate": 0.15
}