{
  "last_update": "2025-12-26T20:19:09.304072",
  "total_draws": 500,
  "draws": [
    {
      "date": "26.12.2025",
      "number": "914951"
    },
    {
      "date": "22.12.2025",
      "number": "309422"
    },
    {
      "date": "20.12.2025",
      "number": "178579"
    },
    {
      "date": "16.12.2025",
      "number": "660456"
    },
    {
      "date": "14.12.2025",
      "number": "143209"
    },
    {
      "date": "10.12.2025",
      "number": "609348"
    },
    {
      "date": "08.12.2025",
      "number": "110831"
    },
    {
      "date": "04.12.2025",
      "number": "777876"
    },
    {
      "date": "02.11.2025",
      "number": "741790"
    },
    {
      "date": "26.11.2025",
      "number": "585948"
    },
    {
      "date": "24.11.2025",
      "number": "045821"
    },
    {
      "date": "20.11.2025",
      "number": "216367"
    },
    {
      "date": "18.11.2025",
      "number": "931612"
    },
    {
      "date": "14.11.2025",
      "number": "336405"
    },
    {
      "date": "12.11.2025",
      "number": "502861"
    },
    {
      "date": "08.11.2025",
      "number": "027588"
    },
    {
      "date": "06.10.2025",
      "number": "447304"
    },
    {
      "date": "02.10.2025",
      "number": "197872"
    },
    {
      "date": "01.10.2025",
      "number": "458450"
    },
    {
      "date": "24.10.2025",
      "number": "778608"
    },
    {
      "date": "22.10.2025",
      "number": "285858"
    },
    {
      "date": "18.10.2025",
      "number": "172022"
    },
    {
      "date": "16.10.2025",
      "number": "919857"
    },
    {
      "date": "12.10.2025",
      "number": "729568"
    },
    {
      "date": "10.09.2025",
      "number": "652400"
    },
    {
      "date": "06.09.2025",
      "number": "781127"
    },
    {
      "date": "04.09.2025",
      "number": "262305"
    },
    {
      "date": "01.09.2025",
      "number": "535732"
    },
    {
      "date": "26.09.2025",
      "number": "867144"
    },
    {
      "date": "22.09.2025",
      "number": "265790"
    },
    {
      "date": "20.09.2025",
      "number": "556864"
    },
    {
      "date": "16.09.2025",
      "number": "247178"
    },
    {
      "date": "14.08.2025",
      "number": "481958"
    },
    {
      "date": "10.08.2025",
      "number": "943818"
    },
    {
      "date": "08.08.2025",
      "number": "171541"
    },
    {
      "date": "04.08.2025",
      "number": "208712"
    },
    {
      "date": "02.08.2025",
      "number": "345450"
    },
    {
      "date": "26.08.2025",
      "number": "562313"
    },
    {
      "date": "24.08.2025",
      "number": "690021"
    },
    {
      "date": "20.08.2025",
      "number": "534781"
    },
    {
      "date": "18.07.2025",
      "number": "434008"
    },
    {
      "date": "14.07.2025",
      "number": "986287"
    },
    {
      "date": "12.07.2025",
      "number": "007950"
    },
    {
      "date": "08.07.2025",
      "number": "785896"
    },
    {
      "date": "06.07.2025",
      "number": "594165"
    },
    {
      "date": "02.07.2025",
      "number": "954240"
    },
    {
      "date": "01.07.2025",
      "number": "831589"
    },
    {
      "date": "24.07.2025",
      "number": "749599"
    },
    {
      "date": "22.06.2025",
      "number": "852919"
    },
    {
      "date": "18.06.2025",
      "number": "095722"
    },
    {
      "date": "16.06.2025",
      "number": "957601"
    },
    {
      "date": "12.06.2025",
      "number": "145618"
    },
    {
      "date": "10.06.2025",
      "number": "558997"
    },
    {
      "date": "06.06.2025",
      "number": "955448"
    },
    {
      "date": "04.06.2025",
      "number": "713754"
    },
    {
      "date": "01.06.2025",
      "number": "408477"
    },
    {
      "date": "26.05.2025",
      "number": "028389"
    },
    {
      "date": "22.05.2025",
      "number": "571739"
    },
    {
      "date": "20.05.2025",
      "number": "526856"
    },
    {
      "date": "16.05.2025",
      "number": "964197"
    },
    {
      "date": "14.05.2025",
      "number": "757073"
    },
    {
      "date": "10.05.2025",
      "number": "351633"
    },
    {
      "date": "08.05.2025",
      "number": "888834"
    },
    {
      "date": "04.05.2025",
      "number": "737824"
    },
    {
      "date": "02.04.2025",
      "number": "425515"
    },
    {
      "date": "26.04.2025",
      "number": "751560"
    },
    {
      "date": "24.04.2025",
      "number": "158531"
    },
    {
      "date": "20.04.2025",
      "number": "503359"
    },
    {
      "date": "18.04.2025",
      "number": "269576"
    },
    {
      "date": "14.04.2025",
      "number": "158780"
    },
    {
      "date": "12.04.2025",
      "number": "999423"
    },
    {
      "date": "08.04.2025",
      "number": "957757"
    },
    {
      "date": "06.03.2025",
      "number": "601957"
    },
    {
      "date": "02.03.2025",
      "number": "748774"
    },
    {
      "date": "01.03.2025",
      "number": "873058"
    },
    {
      "date": "24.03.2025",
      "number": "943644"
    },
    {
      "date": "22.03.2025",
      "number": "167513"
    },
    {
      "date": "18.03.2025",
      "number": "196163"
    },
    {
      "date": "16.03.2025",
      "number": "906098"
    },
    {
      "date": "12.03.2025",
      "number": "370715"
    },
    {
      "date": "10.02.2025",
      "number": "540874"
    },
    {
      "date": "06.02.2025",
      "number": "224826"
    },
    {
      "date": "04.02.2025",
      "number": "451994"
    },
    {
      "date": "01.02.2025",
      "number": "364182"
    },
    {
      "date": "26.02.2025",
      "number": "737454"
    },
    {
      "date": "22.02.2025",
      "number": "474594"
    },
    {
      "date": "20.02.2025",
      "number": "689622"
    },
    {
      "date": "16.02.2025",
      "number": "374218"
    },
    {
      "date": "14.01.2025",
      "number": "543784"
    },
    {
      "date": "10.01.2025",
      "number": "326425"
    },
    {
      "date": "08.01.2025",
      "number": "734923"
    },
    {
      "date": "04.01.2025",
      "number": "164092"
    },
    {
      "date": "02.01.2025",
      "number": "194479"
    },
    {
      "date": "26.01.2025",
      "number": "679873"
    },
    {
      "date": "24.01.2025",
      "number": "948275"
    },
    {
      "date": "20.01.2025",
      "number": "090304"
    },
    {
      "date": "18.12.2024",
      "number": "154130"
    },
    {
      "date": "14.12.2024",
      "number": "170778"
    },
    {
      "date": "12.12.2024",
      "number": "472762"
    },
    {
      "date": "08.12.2024",
      "number": "545195"
    },
    {
      "date": "06.12.2024",
      "number": "180970"
    },
    {
      "date": "02.12.2024",
      "number": "073565"
    },
    {
      "date": "01.12.2024",
      "number": "655311"
    },
    {
      "date": "24.12.2024",
      "number": "737214"
    },
    {
      "date": "22.11.2024",
      "number": "685473"
    },
    {
      "date": "18.11.2024",
      "number": "843180"
    },
    {
      "date": "16.11.2024",
      "number": "557217"
    },
    {
      "date": "12.11.2024",
      "number": "937484"
    },
    {
      "date": "10.11.2024",
      "number": "864761"
    },
    {
      "date": "06.11.2024",
      "number": "185879"
    },
    {
      "date": "04.11.2024",
      "number": "213371"
    },
    {
      "date": "01.11.2024",
      "number": "727364"
    },
    {
      "date": "26.10.2024",
      "number": "416931"
    },
    {
      "date": "22.10.2024",
      "number": "647330"
    },
    {
      "date": "20.10.2024",
      "number": "100130"
    },
    {
      "date": "16.10.2024",
      "number": "737503"
    },
    {
      "date": "14.10.2024",
      "number": "416619"
    },
    {
      "date": "10.10.2024",
      "number": "533796"
    },
    {
      "date": "08.10.2024",
      "number": "809510"
    },
    {
      "date": "04.10.2024",
      "number": "517869"
    },
    {
      "date": "02.09.2024",
      "number": "048209"
    },
    {
      "date": "26.09.2024",
      "number": "753167"
    },
    {
      "date": "24.09.2024",
      "number": "732754"
    },
    {
      "date": "20.09.2024",
      "number": "838461"
    },
    {
      "date": "18.09.2024",
      "number": "885312"
    },
    {
      "date": "14.09.2024",
      "number": "038116"
    },
    {
      "date": "12.09.2024",
      "number": "109024"
    },
    {
      "date": "08.09.2024",
      "number": "980039"
    },
    {
      "date": "06.08.2024",
      "number": "172534"
    },
    {
      "date": "02.08.2024",
      "number": "490495"
    },
    {
      "date": "01.08.2024",
      "number": "080604"
    },
    {
      "date": "24.08.2024",
      "number": "907331"
    },
    {
      "date": "22.08.2024",
      "number": "195378"
    },
    {
      "date": "18.08.2024",
      "number": "987382"
    },
    {
      "date": "16.08.2024",
      "number": "788535"
    },
    {
      "date": "12.08.2024",
      "number": "155779"
    },
    {
      "date": "10.07.2024",
      "number": "200329"
    },
    {
      "date": "06.07.2024",
      "number": "580429"
    },
    {
      "date": "04.07.2024",
      "number": "553706"
    },
    {
      "date": "01.07.2024",
      "number": "895475"
    },
    {
      "date": "26.07.2024",
      "number": "059873"
    },
    {
      "date": "22.07.2024",
      "number": "215171"
    },
    {
      "date": "20.07.2024",
      "number": "600834"
    },
    {
      "date": "16.07.2024",
      "number": "073363"
    },
    {
      "date": "14.06.2024",
      "number": "241706"
    },
    {
      "date": "10.06.2024",
      "number": "931086"
    },
    {
      "date": "08.06.2024",
      "number": "287723"
    },
    {
      "date": "04.06.2024",
      "number": "412517"
    },
    {
      "date": "02.06.2024",
      "number": "225677"
    },
    {
      "date": "26.06.2024",
      "number": "427789"
    },
    {
      "date": "24.06.2024",
      "number": "052451"
    },
    {
      "date": "20.06.2024",
      "number": "149810"
    },
    {
      "date": "18.05.2024",
      "number": "967709"
    },
    {
      "date": "14.05.2024",
      "number": "121684"
    },
    {
      "date": "12.05.2024",
      "number": "068265"
    },
    {
      "date": "08.05.2024",
      "number": "164435"
    },
    {
      "date": "06.05.2024",
      "number": "087042"
    },
    {
      "date": "02.05.2024",
      "number": "226900"
    },
    {
      "date": "01.05.2024",
      "number": "434896"
    },
    {
      "date": "24.05.2024",
      "number": "863989"
    },
    {
      "date": "22.04.2024",
      "number": "294900"
    },
    {
      "date": "18.04.2024",
      "number": "638635"
    },
    {
      "date": "16.04.2024",
      "number": "656547"
    },
    {
      "date": "12.04.2024",
      "number": "150641"
    },
    {
      "date": "10.04.2024",
      "number": "214160"
    },
    {
      "date": "06.04.2024",
      "number": "059226"
    },
    {
      "date": "04.04.2024",
      "number": "989670"
    },
    {
      "date": "01.04.2024",
      "number": "750094"
    },
    {
      "date": "26.03.2024",
      "number": "426205"
    },
    {
      "date": "22.03.2024",
      "number": "677340"
    },
    {
      "date": "20.03.2024",
      "number": "215969"
    },
    {
      "date": "16.03.2024",
      "number": "875634"
    },
    {
      "date": "14.03.2024",
      "number": "887095"
    },
    {
      "date": "10.03.2024",
      "number": "222205"
    },
    {
      "date": "08.03.2024",
      "number": "109615"
    },
    {
      "date": "04.03.2024",
      "number": "774549"
    },
    {
      "date": "02.02.2024",
      "number": "070159"
    },
    {
      "date": "26.02.2024",
      "number": "647528"
    },
    {
      "date": "24.02.2024",
      "number": "712472"
    },
    {
      "date": "20.02.2024",
      "number": "676052"
    },
    {
      "date": "18.02.2024",
      "number": "164192"
    },
    {
      "date": "14.02.2024",
      "number": "072987"
    },
    {
      "date": "12.02.2024",
      "number": "911711"
    },
    {
      "date": "08.02.2024",
      "number": "109047"
    },
    {
      "date": "06.01.2024",
      "number": "315412"
    },
    {
      "date": "02.01.2024",
      "number": "507153"
    },
    {
      "date": "01.01.2024",
      "number": "233289"
    },
    {
      "date": "24.01.2024",
      "number": "573874"
    },
    {
      "date": "22.01.2024",
      "number": "872555"
    },
    {
      "date": "18.01.2024",
      "number": "303854"
    },
    {
      "date": "16.01.2024",
      "number": "450516"
    },
    {
      "date": "12.01.2024",
      "number": "886576"
    },
    {
      "date": "10.12.2023",
      "number": "837880"
    },
    {
      "date": "06.12.2023",
      "number": "209436"
    },
    {
      "date": "04.12.2023",
      "number": "484625"
    },
    {
      "date": "01.12.2023",
      "number": "014710"
    },
    {
      "date": "26.12.2023",
      "number": "196082"
    },
    {
      "date": "22.12.2023",
      "number": "774307"
    },
    {
      "date": "20.12.2023",
      "number": "112978"
    },
    {
      "date": "16.12.2023",
      "number": "115395"
    },
    {
      "date": "14.11.2023",
      "number": "561431"
    },
    {
      "date": "10.11.2023",
      "number": "647260"
    },
    {
      "date": "08.11.2023",
      "number": "046681"
    },
    {
      "date": "04.11.2023",
      "number": "606172"
    },
    {
      "date": "02.11.2023",
      "number": "304130"
    },
    {
      "date": "26.11.2023",
      "number": "911607"
    },
    {
      "date": "24.11.2023",
      "number": "987203"
    },
    {
      "date": "20.11.2023",
      "number": "150985"
    },
    {
      "date": "18.10.2023",
      "number": "689944"
    },
    {
      "date": "14.10.2023",
      "number": "729580"
    },
    {
      "date": "12.10.2023",
      "number": "927577"
    },
    {
      "date": "08.10.2023",
      "number": "144157"
    },
    {
      "date": "06.10.2023",
      "number": "335097"
    },
    {
      "date": "02.10.2023",
      "number": "249538"
    },
    {
      "date": "01.10.2023",
      "number": "852640"
    },
    {
      "date": "24.10.2023",
      "number": "270404"
    },
    {
      "date": "22.09.2023",
      "number": "841580"
    },
    {
      "date": "18.09.2023",
      "number": "155057"
    },
    {
      "date": "16.09.2023",
      "number": "483493"
    },
    {
      "date": "12.09.2023",
      "number": "323860"
    },
    {
      "date": "10.09.2023",
      "number": "921018"
    },
    {
      "date": "06.09.2023",
      "number": "683837"
    },
    {
      "date": "04.09.2023",
      "number": "367959"
    },
    {
      "date": "01.09.2023",
      "number": "119558"
    },
    {
      "date": "26.08.2023",
      "number": "545106"
    },
    {
      "date": "22.08.2023",
      "number": "837527"
    },
    {
      "date": "20.08.2023",
      "number": "877830"
    },
    {
      "date": "16.08.2023",
      "number": "861011"
    },
    {
      "date": "14.08.2023",
      "number": "872407"
    },
    {
      "date": "10.08.2023",
      "number": "883701"
    },
    {
      "date": "08.08.2023",
      "number": "281196"
    },
    {
      "date": "04.08.2023",
      "number": "506444"
    },
    {
      "date": "02.07.2023",
      "number": "503600"
    },
    {
      "date": "26.07.2023",
      "number": "085683"
    },
    {
      "date": "24.07.2023",
      "number": "960415"
    },
    {
      "date": "20.07.2023",
      "number": "932368"
    },
    {
      "date": "18.07.2023",
      "number": "745489"
    },
    {
      "date": "14.07.2023",
      "number": "654399"
    },
    {
      "date": "12.07.2023",
      "number": "930953"
    },
    {
      "date": "08.07.2023",
      "number": "083080"
    },
    {
      "date": "06.06.2023",
      "number": "173505"
    },
    {
      "date": "02.06.2023",
      "number": "978788"
    },
    {
      "date": "01.06.2023",
      "number": "681262"
    },
    {
      "date": "24.06.2023",
      "number": "386587"
    },
    {
      "date": "22.06.2023",
      "number": "044274"
    },
    {
      "date": "18.06.2023",
      "number": "738303"
    },
    {
      "date": "16.06.2023",
      "number": "104273"
    },
    {
      "date": "12.06.2023",
      "number": "734003"
    },
    {
      "date": "10.05.2023",
      "number": "583629"
    },
    {
      "date": "06.05.2023",
      "number": "454364"
    },
    {
      "date": "04.05.2023",
      "number": "771201"
    },
    {
      "date": "01.05.2023",
      "number": "859935"
    },
    {
      "date": "26.05.2023",
      "number": "995858"
    },
    {
      "date": "22.05.2023",
      "number": "011398"
    },
    {
      "date": "20.05.2023",
      "number": "526403"
    },
    {
      "date": "16.05.2023",
      "number": "064690"
    },
    {
      "date": "14.04.2023",
      "number": "166830"
    },
    {
      "date": "10.04.2023",
      "number": "343084"
    },
    {
      "date": "08.04.2023",
      "number": "901731"
    },
    {
      "date": "04.04.2023",
      "number": "969868"
    },
    {
      "date": "02.04.2023",
      "number": "123489"
    },
    {
      "date": "26.04.2023",
      "number": "429364"
    },
    {
      "date": "24.04.2023",
      "number": "691411"
    },
    {
      "date": "20.04.2023",
      "number": "993486"
    },
    {
      "date": "18.03.2023",
      "number": "406278"
    },
    {
      "date": "14.03.2023",
      "number": "562148"
    },
    {
      "date": "12.03.2023",
      "number": "129857"
    },
    {
      "date": "08.03.2023",
      "number": "133518"
    },
    {
      "date": "06.03.2023",
      "number": "493591"
    },
    {
      "date": "02.03.2023",
      "number": "385553"
    },
    {
      "date": "01.03.2023",
      "number": "723520"
    },
    {
      "date": "24.03.2023",
      "number": "904632"
    },
    {
      "date": "22.02.2023",
      "number": "117062"
    },
    {
      "date": "18.02.2023",
      "number": "183440"
    },
    {
      "date": "16.02.2023",
      "number": "533290"
    },
    {
      "date": "12.02.2023",
      "number": "348938"
    },
    {
      "date": "10.02.2023",
      "number": "958711"
    },
    {
      "date": "06.02.2023",
      "number": "599843"
    },
    {
      "date": "04.02.2023",
      "number": "992259"
    },
    {
      "date": "01.02.2023",
      "number": "429934"
    },
    {
      "date": "26.01.2023",
      "number": "080851"
    },
    {
      "date": "22.01.2023",
      "number": "996893"
    },
    {
      "date": "20.01.2023",
      "number": "728323"
    },
    {
      "date": "16.01.2023",
      "number": "741065"
    },
    {
      "date": "14.01.2023",
      "number": "860707"
    },
    {
      "date": "10.01.2023",
      "number": "069160"
    },
    {
      "date": "08.01.2023",
      "number": "859876"
    },
    {
      "date": "04.01.2023",
      "number": "858216"
    },
    {
      "date": "02.12.2022",
      "number": "253937"
    },
    {
      "date": "26.12.2022",
      "number": "963596"
    },
    {
      "date": "24.12.2022",
      "number": "856501"
    },
    {
      "date": "20.12.2022",
      "number": "061459"
    },
    {
      "date": "18.12.2022",
      "number": "647262"
    },
    {
      "date": "14.12.2022",
      "number": "209991"
    },
    {
      "date": "12.12.2022",
      "number": "419987"
    },
    {
      "date": "08.12.2022",
      "number": "310349"
    },
    {
      "date": "06.11.2022",
      "number": "347450"
    },
    {
      "date": "02.11.2022",
      "number": "148366"
    },
    {
      "date": "01.11.2022",
      "number": "704040"
    },
    {
      "date": "24.11.2022",
      "number": "004248"
    },
    {
      "date": "22.11.2022",
      "number": "612674"
    },
    {
      "date": "18.11.2022",
      "number": "609951"
    },
    {
      "date": "16.11.2022",
      "number": "838541"
    },
    {
      "date": "12.11.2022",
      "number": "117453"
    },
    {
      "date": "10.10.2022",
      "number": "703020"
    },
    {
      "date": "06.10.2022",
      "number": "446282"
    },
    {
      "date": "04.10.2022",
      "number": "325196"
    },
    {
      "date": "01.10.2022",
      "number": "226657"
    },
    {
      "date": "26.10.2022",
      "number": "594462"
    },
    {
      "date": "22.10.2022",
      "number": "282753"
    },
    {
      "date": "20.10.2022",
      "number": "771333"
    },
    {
      "date": "16.10.2022",
      "number": "021090"
    },
    {
      "date": "14.09.2022",
      "number": "631208"
    },
    {
      "date": "10.09.2022",
      "number": "521059"
    },
    {
      "date": "08.09.2022",
      "number": "723640"
    },
    {
      "date": "04.09.2022",
      "number": "436314"
    },
    {
      "date": "02.09.2022",
      "number": "002804"
    },
    {
      "date": "26.09.2022",
      "number": "779849"
    },
    {
      "date": "24.09.2022",
      "number": "029725"
    },
    {
      "date": "20.09.2022",
      "number": "752608"
    },
    {
      "date": "18.08.2022",
      "number": "921901"
    },
    {
      "date": "14.08.2022",
      "number": "344275"
    },
    {
      "date": "12.08.2022",
      "number": "073328"
    },
    {
      "date": "08.08.2022",
      "number": "854683"
    },
    {
      "date": "06.08.2022",
      "number": "824255"
    },
    {
      "date": "02.08.2022",
      "number": "011429"
    },
    {
      "date": "01.08.2022",
      "number": "398188"
    },
    {
      "date": "24.08.2022",
      "number": "537059"
    },
    {
      "date": "22.07.2022",
      "number": "556451"
    },
    {
      "date": "18.07.2022",
      "number": "277761"
    },
    {
      "date": "16.07.2022",
      "number": "530524"
    },
    {
      "date": "12.07.2022",
      "number": "213372"
    },
    {
      "date": "10.07.2022",
      "number": "075402"
    },
    {
      "date": "06.07.2022",
      "number": "668174"
    },
    {
      "date": "04.07.2022",
      "number": "056286"
    },
    {
      "date": "01.07.2022",
      "number": "101206"
    },
    {
      "date": "26.06.2022",
      "number": "210026"
    },
    {
      "date": "22.06.2022",
      "number": "478853"
    },
    {
      "date": "20.06.2022",
      "number": "409822"
    },
    {
      "date": "16.06.2022",
      "number": "113499"
    },
    {
      "date": "14.06.2022",
      "number": "031328"
    },
    {
      "date": "10.06.2022",
      "number": "480283"
    },
    {
      "date": "08.06.2022",
      "number": "144646"
    },
    {
      "date": "04.06.2022",
      "number": "817380"
    },
    {
      "date": "02.05.2022",
      "number": "784893"
    },
    {
      "date": "26.05.2022",
      "number": "087416"
    },
    {
      "date": "24.05.2022",
      "number": "393584"
    },
    {
      "date": "20.05.2022",
      "number": "168947"
    },
    {
      "date": "18.05.2022",
      "number": "981281"
    },
    {
      "date": "14.05.2022",
      "number": "468190"
    },
    {
      "date": "12.05.2022",
      "number": "750386"
    },
    {
      "date": "08.05.2022",
      "number": "920447"
    },
    {
      "date": "06.04.2022",
      "number": "789762"
    },
    {
      "date": "02.04.2022",
      "number": "418331"
    },
    {
      "date": "01.04.2022",
      "number": "705423"
    },
    {
      "date": "24.04.2022",
      "number": "110067"
    },
    {
      "date": "22.04.2022",
      "number": "341619"
    },
    {
      "date": "18.04.2022",
      "number": "441275"
    },
    {
      "date": "16.04.2022",
      "number": "105456"
    },
    {
      "date": "12.04.2022",
      "number": "224372"
    },
    {
      "date": "10.03.2022",
      "number": "583130"
    },
    {
      "date": "06.03.2022",
      "number": "393644"
    },
    {
      "date": "04.03.2022",
      "number": "965772"
    },
    {
      "date": "01.03.2022",
      "number": "746949"
    },
    {
      "date": "26.03.2022",
      "number": "543288"
    },
    {
      "date": "22.03.2022",
      "number": "099016"
    },
    {
      "date": "20.03.2022",
      "number": "420585"
    },
    {
      "date": "16.03.2022",
      "number": "099870"
    },
    {
      "date": "14.02.2022",
      "number": "709437"
    },
    {
      "date": "10.02.2022",
      "number": "514840"
    },
    {
      "date": "08.02.2022",
      "number": "572843"
    },
    {
      "date": "04.02.2022",
      "number": "189813"
    },
    {
      "date": "02.02.2022",
      "number": "745600"
    },
    {
      "date": "26.02.2022",
      "number": "564954"
    },
    {
      "date": "24.02.2022",
      "number": "177469"
    },
    {
      "date": "20.02.2022",
      "number": "907333"
    },
    {
      "date": "18.01.2022",
      "number": "239248"
    },
    {
      "date": "14.01.2022",
      "number": "709208"
    },
    {
      "date": "12.01.2022",
      "number": "329836"
    },
    {
      "date": "08.01.2022",
      "number": "670244"
    },
    {
      "date": "06.01.2022",
      "number": "936795"
    },
    {
      "date": "02.01.2022",
      "number": "849748"
    },
    {
      "date": "01.01.2022",
      "number": "422971"
    },
    {
      "date": "24.01.2022",
      "number": "295422"
    },
    {
      "date": "22.12.2021",
      "number": "712446"
    },
    {
      "date": "18.12.2021",
      "number": "271920"
    },
    {
      "date": "16.12.2021",
      "number": "274736"
    },
    {
      "date": "12.12.2021",
      "number": "770581"
    },
    {
      "date": "10.12.2021",
      "number": "862043"
    },
    {
      "date": "06.12.2021",
      "number": "622180"
    },
    {
      "date": "04.12.2021",
      "number": "541406"
    },
    {
      "date": "01.12.2021",
      "number": "153499"
    },
    {
      "date": "26.11.2021",
      "number": "618869"
    },
    {
      "date": "22.11.2021",
      "number": "377467"
    },
    {
      "date": "20.11.2021",
      "number": "020520"
    },
    {
      "date": "16.11.2021",
      "number": "118762"
    },
    {
      "date": "14.11.2021",
      "number": "959853"
    },
    {
      "date": "10.11.2021",
      "number": "521302"
    },
    {
      "date": "08.11.2021",
      "number": "596809"
    },
    {
      "date": "04.11.2021",
      "number": "398295"
    },
    {
      "date": "02.10.2021",
      "number": "447448"
    },
    {
      "date": "26.10.2021",
      "number": "872196"
    },
    {
      "date": "24.10.2021",
      "number": "665318"
    },
    {
      "date": "20.10.2021",
      "number": "014874"
    },
    {
      "date": "18.10.2021",
      "number": "222835"
    },
    {
      "date": "14.10.2021",
      "number": "086475"
    },
    {
      "date": "12.10.2021",
      "number": "622382"
    },
    {
      "date": "08.10.2021",
      "number": "923634"
    },
    {
      "date": "06.09.2021",
      "number": "811168"
    },
    {
      "date": "02.09.2021",
      "number": "503942"
    },
    {
      "date": "01.09.2021",
      "number": "466521"
    },
    {
      "date": "24.09.2021",
      "number": "167622"
    },
    {
      "date": "22.09.2021",
      "number": "140685"
    },
    {
      "date": "18.09.2021",
      "number": "351074"
    },
    {
      "date": "16.09.2021",
      "number": "458805"
    },
    {
      "date": "12.09.2021",
      "number": "708660"
    },
    {
      "date": "10.08.2021",
      "number": "713145"
    },
    {
      "date": "06.08.2021",
      "number": "017893"
    },
    {
      "date": "04.08.2021",
      "number": "549342"
    },
    {
      "date": "01.08.2021",
      "number": "986305"
    },
    {
      "date": "26.08.2021",
      "number": "205648"
    },
    {
      "date": "22.08.2021",
      "number": "697810"
    },
    {
      "date": "20.08.2021",
      "number": "186561"
    },
    {
      "date": "16.08.2021",
      "number": "032211"
    },
    {
      "date": "14.07.2021",
      "number": "706614"
    },
    {
      "date": "10.07.2021",
      "number": "789868"
    },
    {
      "date": "08.07.2021",
      "number": "013671"
    },
    {
      "date": "04.07.2021",
      "number": "100778"
    },
    {
      "date": "02.07.2021",
      "number": "324342"
    },
    {
      "date": "26.07.2021",
      "number": "726655"
    },
    {
      "date": "24.07.2021",
      "number": "946858"
    },
    {
      "date": "20.07.2021",
      "number": "684882"
    },
    {
      "date": "18.06.2021",
      "number": "390472"
    },
    {
      "date": "14.06.2021",
      "number": "761680"
    },
    {
      "date": "12.06.2021",
      "number": "177395"
    },
    {
      "date": "08.06.2021",
      "number": "661431"
    },
    {
      "date": "06.06.2021",
      "number": "796486"
    },
    {
      "date": "02.06.2021",
      "number": "186757"
    },
    {
      "date": "01.06.2021",
      "number": "854516"
    },
    {
      "date": "24.06.2021",
      "number": "188930"
    },
    {
      "date": "22.05.2021",
      "number": "973829"
    },
    {
      "date": "18.05.2021",
      "number": "340253"
    },
    {
      "date": "16.05.2021",
      "number": "971843"
    },
    {
      "date": "12.05.2021",
      "number": "520584"
    },
    {
      "date": "10.05.2021",
      "number": "908868"
    },
    {
      "date": "06.05.2021",
      "number": "693213"
    },
    {
      "date": "04.05.2021",
      "number": "118298"
    },
    {
      "date": "01.05.2021",
      "number": "598999"
    },
    {
      "date": "26.04.2021",
      "number": "461316"
    },
    {
      "date": "22.04.2021",
      "number": "515945"
    },
    {
      "date": "20.04.2021",
      "number": "277247"
    },
    {
      "date": "16.04.2021",
      "number": "030526"
    },
    {
      "date": "14.04.2021",
      "number": "581657"
    },
    {
      "date": "10.04.2021",
      "number": "807667"
    },
    {
      "date": "08.04.2021",
      "number": "992345"
    },
    {
      "date": "04.04.2021",
      "number": "316693"
    },
    {
      "date": "02.03.2021",
      "number": "083572"
    },
    {
      "date": "26.03.2021",
      "number": "541840"
    },
    {
      "date": "24.03.2021",
      "number": "600772"
    },
    {
      "date": "20.03.2021",
      "number": "768484"
    },
    {
      "date": "18.03.2021",
      "number": "449145"
    },
    {
      "date": "14.03.2021",
      "number": "665841"
    },
    {
      "date": "12.03.2021",
      "number": "618371"
    },
    {
      "date": "08.03.2021",
      "number": "556142"
    },
    {
      "date": "06.02.2021",
      "number": "709546"
    },
    {
      "date": "02.02.2021",
      "number": "616606"
    },
    {
      "date": "01.02.2021",
      "number": "278941"
    },
    {
      "date": "24.02.2021",
      "number": "300448"
    },
    {
      "date": "22.02.2021",
      "number": "517058"
    },
    {
      "date": "18.02.2021",
      "number": "075662"
    },
    {
      "date": "16.02.2021",
      "number": "453632"
    },
    {
      "date": "12.02.2021",
      "number": "234763"
    },
    {
      "date": "10.01.2021",
      "number": "546362"
    },
    {
      "date": "06.01.2021",
      "number": "036109"
    },
    {
      "date": "04.01.2021",
      "number": "353554"
    },
    {
      "date": "01.01.2021",
      "number": "073712"
    },
    {
      "date": "26.01.2021",
      "number": "027011"
    },
    {
      "date": "22.01.2021",
      "number": "251817"
    },
    {
      "date": "20.01.2021",
      "number": "129516"
    },
    {
      "date": "16.01.2021",
      "number": "883740"
    },
    {
      "date": "14.12.2020",
      "number": "330010"
    },
    {
      "date": "10.12.2020",
      "number": "298871"
    },
    {
      "date": "08.12.2020",
      "number": "305148"
    },
    {
      "date": "04.12.2020",
      "number": "991250"
    },
    {
      "date": "02.12.2020",
      "number": "394700"
    },
    {
      "date": "26.12.2020",
      "number": "539258"
    },
    {
      "date": "24.12.2020",
      "number": "581853"
    },
    {
      "date": "20.12.2020",
      "number": "762456"
    },
    {
      "date": "18.11.2020",
      "number": "826934"
    },
    {
      "date": "14.11.2020",
      "number": "110842"
    },
    {
      "date": "12.11.2020",
      "number": "819303"
    },
    {
      "date": "08.11.2020",
      "number": "374725"
    },
    {
      "date": "06.11.2020",
      "number": "862840"
    },
    {
      "date": "02.11.2020",
      "number": "533571"
    },
    {
      "date": "01.11.2020",
      "number": "155465"
    },
    {
      "date": "24.11.2020",
      "number": "975640"
    },
    {
      "date": "22.10.2020",
      "number": "481295"
    },
    {
      "date": "18.10.2020",
      "number": "331954"
    },
    {
      "date": "16.10.2020",
      "number": "089699"
    },
    {
      "date": "12.10.2020",
      "number": "141618"
    }
  ],
  "note": "Demo-Daten - echte historische Daten werden nachgeladen"
}